Metadata-Version: 1.1
Name: hands-chopping
Version: 0.3.0
Summary: Search goods in shopping web, It' time to chop your hands.
Home-page: https://github.com/ecmadao/Hands-Chopping
Author: ecmadao
Author-email: wlec@outlook.com
License: MIT
Keywords: taobao,jingdong,hands chopping,spider
Platform: any
Classifier: Environment :: Console
Classifier: Programming Language :: Python
Classifier: Programming Language :: Python :: 3.5
Classifier: Programming Language :: Python :: Implementation :: CPython
